<?xml version="1.0" encoding="UTF-8"?>
<launch4jConfig>
  <dontWrapJar>false</dontWrapJar>
  <headerType>gui</headerType>
  <jar>D:\Projekte\EduFTP\target\EduFTP-1.0-SNAPSHOT-jar-with-dependencies.jar</jar>
  <outfile>D:\Projekte\EduFTP\target\EduFTP.exe</outfile>
  <errTitle></errTitle>
  <cmdLine></cmdLine>
  <chdir>.</chdir>
  <priority>normal</priority>
  <downloadUrl>http://java.com/download</downloadUrl>
  <supportUrl></supportUrl>
  <stayAlive>false</stayAlive>
  <restartOnCrash>false</restartOnCrash>
  <manifest></manifest>
  <icon></icon>
  <classPath>
    <mainClass>de.lorenzotoso.MainDialog</mainClass>
    <cp>commons-io-2.5.jar</cp>
    <cp>commons-net-3.6.jar</cp>
  </classPath>
  <jre>
    <path></path>
    <bundledJre64Bit>false</bundledJre64Bit>
    <bundledJreAsFallback>false</bundledJreAsFallback>
    <minVersion>1.8.0_131</minVersion>
    <maxVersion></maxVersion>
    <jdkPreference>preferJre</jdkPreference>
    <runtimeBits>64/32</runtimeBits>
  </jre>
</launch4jConfig>